conversor_binario/__init__.py
conversor_binario/conversor.py
conversor_binario-0.1.dist-info/METADATA
conversor_binario-0.1.dist-info/WHEEL
conversor_binario-0.1.dist-info/top_level.txt
conversor_binario-0.1.dist-info/RECORD
