Metadata-Version: 2.1
Name: conversor_binario
Version: 0.1
Summary: Um pacote para converter números binários para decimal, octal e hexadecimal.
Author: Tiago
Classifier: Programming Language :: Python :: 3
Classifier: License :: OSI Approved :: MIT License
Classifier: Operating System :: OS Independent
Requires-Python: >=3.6
